{
	"configurations" : 
	[
		{
			"directories" : 
			[
				{
					"build" : ".",
					"childIndexes" : 
					[
						1
					],
					"minimumCMakeVersion" : 
					{
						"string" : "2.8"
					},
					"projectIndex" : 0,
					"source" : "."
				},
				{
					"build" : "GvRAWDataLoader",
					"minimumCMakeVersion" : 
					{
						"string" : "2.8"
					},
					"parentIndex" : 0,
					"projectIndex" : 1,
					"source" : "GvRAWDataLoader",
					"targetIndexes" : 
					[
						0
					]
				}
			],
			"name" : "Debug",
			"projects" : 
			[
				{
					"childIndexes" : 
					[
						1
					],
					"directoryIndexes" : 
					[
						0
					],
					"name" : "ViewerPluginTutorials"
				},
				{
					"directoryIndexes" : 
					[
						1
					],
					"name" : "GvRAWDataLoader",
					"parentIndex" : 0,
					"targetIndexes" : 
					[
						0
					]
				}
			],
			"targets" : 
			[
				{
					"directoryIndex" : 1,
					"id" : "GvRAWDataLoader::@1b8f574ee46dd50327a9",
					"jsonFile" : "target-GvRAWDataLoader-Debug-f57441096b83042c85ff.json",
					"name" : "GvRAWDataLoader",
					"projectIndex" : 1
				}
			]
		}
	],
	"kind" : "codemodel",
	"paths" : 
	{
		"build" : "D:/GVDev/Development/Tutorials/ViewerPlugins/out/build/x64-Debug",
		"source" : "D:/GVDev/Development/Tutorials/ViewerPlugins"
	},
	"version" : 
	{
		"major" : 2,
		"minor" : 2
	}
}
